migranite
