Metadata-Version: 1.1
Name: migranite
Version: 0.4.0
Summary: Migranite -- manage migtations tool
Home-page: https://github.com/zzzsochi/migranite
Author: UNKNOWN
Author-email: UNKNOWN
License: UNKNOWN
Keywords: migrations,development
Platform: UNKNOWN
Classifier: License :: OSI Approved :: BSD License
Classifier: Operating System :: POSIX
Classifier: Programming Language :: Python :: 3.3
Classifier: Programming Language :: Python :: 3.4
Classifier: Programming Language :: Python :: 3.5
Classifier: Topic :: Software Development
